{
	"frames": {
		"Ava_Vip": {
			"frame": {
				"x": 3,
				"y": 3,
				"w": 240,
				"h": 162
			},
			"rotated": false,
			"trimmed": false,
			"spriteSourceSize": {
				"x": 0,
				"y": 0,
				"w": 240,
				"h": 162
			},
			"sourceSize": {
				"w": 240,
				"h": 162
			}
		},
		"Button_Dong_Y": {
			"frame": {
				"x": 246,
				"y": 3,
				"w": 159,
				"h": 50
			},
			"rotated": false,
			"trimmed": false,
			"spriteSourceSize": {
				"x": 0,
				"y": 0,
				"w": 159,
				"h": 50
			},
			"sourceSize": {
				"w": 159,
				"h": 50
			}
		},
		"Button_Thachdau": {
			"frame": {
				"x": 408,
				"y": 3,
				"w": 385,
				"h": 71
			},
			"rotated": false,
			"trimmed": false,
			"spriteSourceSize": {
				"x": 0,
				"y": 0,
				"w": 385,
				"h": 71
			},
			"sourceSize": {
				"w": 385,
				"h": 71
			}
		},
		"Button_Tuchoi": {
			"frame": {
				"x": 3,
				"y": 168,
				"w": 226,
				"h": 71
			},
			"rotated": false,
			"trimmed": false,
			"spriteSourceSize": {
				"x": 0,
				"y": 0,
				"w": 226,
				"h": 71
			},
			"sourceSize": {
				"w": 226,
				"h": 71
			}
		},
		"Button_ket_Ban": {
			"frame": {
				"x": 232,
				"y": 168,
				"w": 385,
				"h": 71
			},
			"rotated": false,
			"trimmed": false,
			"spriteSourceSize": {
				"x": 0,
				"y": 0,
				"w": 385,
				"h": 71
			},
			"sourceSize": {
				"w": 385,
				"h": 71
			}
		},
		"EXP_01": {
			"frame": {
				"x": 620,
				"y": 168,
				"w": 250,
				"h": 7
			},
			"rotated": false,
			"trimmed": false,
			"spriteSourceSize": {
				"x": 0,
				"y": 0,
				"w": 250,
				"h": 7
			},
			"sourceSize": {
				"w": 250,
				"h": 7
			}
		},
		"EXP_02": {
			"frame": {
				"x": 3,
				"y": 242,
				"w": 250,
				"h": 7
			},
			"rotated": false,
			"trimmed": false,
			"spriteSourceSize": {
				"x": 0,
				"y": 0,
				"w": 250,
				"h": 7
			},
			"sourceSize": {
				"w": 250,
				"h": 7
			}
		},
		"Location": {
			"frame": {
				"x": 256,
				"y": 242,
				"w": 16,
				"h": 23
			},
			"rotated": false,
			"trimmed": false,
			"spriteSourceSize": {
				"x": 0,
				"y": 0,
				"w": 16,
				"h": 23
			},
			"sourceSize": {
				"w": 16,
				"h": 23
			}
		},
		"bg_ava_vip": {
			"frame": {
				"x": 275,
				"y": 242,
				"w": 239,
				"h": 160
			},
			"rotated": false,
			"trimmed": false,
			"spriteSourceSize": {
				"x": 0,
				"y": 0,
				"w": 239,
				"h": 160
			},
			"sourceSize": {
				"w": 239,
				"h": 160
			}
		},
		"bg_header": {
			"frame": {
				"x": 3,
				"y": 405,
				"w": 640,
				"h": 124
			},
			"rotated": false,
			"trimmed": false,
			"spriteSourceSize": {
				"x": 0,
				"y": 0,
				"w": 640,
				"h": 124
			},
			"sourceSize": {
				"w": 640,
				"h": 124
			}
		},
		"bg_header_vip": {
			"frame": {
				"x": 3,
				"y": 532,
				"w": 640,
				"h": 124
			},
			"rotated": false,
			"trimmed": false,
			"spriteSourceSize": {
				"x": 0,
				"y": 0,
				"w": 640,
				"h": 124
			},
			"sourceSize": {
				"w": 640,
				"h": 124
			}
		},
		"bg_khung_avatar": {
			"frame": {
				"x": 646,
				"y": 532,
				"w": 159,
				"h": 159
			},
			"rotated": false,
			"trimmed": false,
			"spriteSourceSize": {
				"x": 0,
				"y": 0,
				"w": 159,
				"h": 159
			},
			"sourceSize": {
				"w": 159,
				"h": 159
			}
		},
		"bg_money_user": {
			"frame": {
				"x": 808,
				"y": 532,
				"w": 130,
				"h": 53
			},
			"rotated": false,
			"trimmed": false,
			"spriteSourceSize": {
				"x": 0,
				"y": 0,
				"w": 130,
				"h": 53
			},
			"sourceSize": {
				"w": 130,
				"h": 53
			}
		},
		"button_back": {
			"frame": {
				"x": 941,
				"y": 532,
				"w": 47,
				"h": 47
			},
			"rotated": false,
			"trimmed": false,
			"spriteSourceSize": {
				"x": 0,
				"y": 0,
				"w": 47,
				"h": 47
			},
			"sourceSize": {
				"w": 47,
				"h": 47
			}
		},
		"button_huy_ket_ban": {
			"frame": {
				"x": 3,
				"y": 694,
				"w": 159,
				"h": 50
			},
			"rotated": false,
			"trimmed": false,
			"spriteSourceSize": {
				"x": 0,
				"y": 0,
				"w": 159,
				"h": 50
			},
			"sourceSize": {
				"w": 159,
				"h": 50
			}
		},
		"button_nhan_tin": {
			"frame": {
				"x": 165,
				"y": 694,
				"w": 71,
				"h": 71
			},
			"rotated": false,
			"trimmed": false,
			"spriteSourceSize": {
				"x": 0,
				"y": 0,
				"w": 71,
				"h": 71
			},
			"sourceSize": {
				"w": 71,
				"h": 71
			}
		},
		"button_thach_dau": {
			"frame": {
				"x": 239,
				"y": 694,
				"w": 470,
				"h": 71
			},
			"rotated": false,
			"trimmed": false,
			"spriteSourceSize": {
				"x": 0,
				"y": 0,
				"w": 470,
				"h": 71
			},
			"sourceSize": {
				"w": 470,
				"h": 71
			}
		},
		"button_thach_dau_sort": {
			"frame": {
				"x": 712,
				"y": 694,
				"w": 226,
				"h": 71
			},
			"rotated": false,
			"trimmed": false,
			"spriteSourceSize": {
				"x": 0,
				"y": 0,
				"w": 226,
				"h": 71
			},
			"sourceSize": {
				"w": 226,
				"h": 71
			}
		},
		"button_view_more": {
			"frame": {
				"x": 941,
				"y": 694,
				"w": 47,
				"h": 47
			},
			"rotated": false,
			"trimmed": false,
			"spriteSourceSize": {
				"x": 0,
				"y": 0,
				"w": 47,
				"h": 47
			},
			"sourceSize": {
				"w": 47,
				"h": 47
			}
		},
		"check_offline": {
			"frame": {
				"x": 991,
				"y": 694,
				"w": 18,
				"h": 19
			},
			"rotated": false,
			"trimmed": false,
			"spriteSourceSize": {
				"x": 0,
				"y": 0,
				"w": 18,
				"h": 19
			},
			"sourceSize": {
				"w": 18,
				"h": 19
			}
		},
		"check_online": {
			"frame": {
				"x": 3,
				"y": 768,
				"w": 18,
				"h": 18
			},
			"rotated": false,
			"trimmed": false,
			"spriteSourceSize": {
				"x": 0,
				"y": 0,
				"w": 18,
				"h": 18
			},
			"sourceSize": {
				"w": 18,
				"h": 18
			}
		},
		"icon_diamond": {
			"frame": {
				"x": 24,
				"y": 768,
				"w": 31,
				"h": 22
			},
			"rotated": false,
			"trimmed": false,
			"spriteSourceSize": {
				"x": 0,
				"y": 0,
				"w": 31,
				"h": 22
			},
			"sourceSize": {
				"w": 31,
				"h": 22
			}
		},
		"icon_mic": {
			"frame": {
				"x": 58,
				"y": 768,
				"w": 25,
				"h": 35
			},
			"rotated": false,
			"trimmed": false,
			"spriteSourceSize": {
				"x": 0,
				"y": 0,
				"w": 25,
				"h": 35
			},
			"sourceSize": {
				"w": 25,
				"h": 35
			}
		},
		"icon_ticket": {
			"frame": {
				"x": 86,
				"y": 768,
				"w": 33,
				"h": 24
			},
			"rotated": false,
			"trimmed": false,
			"spriteSourceSize": {
				"x": 0,
				"y": 0,
				"w": 33,
				"h": 24
			},
			"sourceSize": {
				"w": 33,
				"h": 24
			}
		},
		"line_playlist": {
			"frame": {
				"x": 122,
				"y": 768,
				"w": 570,
				"h": 1
			},
			"rotated": false,
			"trimmed": false,
			"spriteSourceSize": {
				"x": 0,
				"y": 0,
				"w": 570,
				"h": 1
			},
			"sourceSize": {
				"w": 570,
				"h": 1
			}
		},
		"top_line_status": {
			"frame": {
				"x": 695,
				"y": 768,
				"w": 160,
				"h": 4
			},
			"rotated": false,
			"trimmed": false,
			"spriteSourceSize": {
				"x": 0,
				"y": 0,
				"w": 160,
				"h": 4
			},
			"sourceSize": {
				"w": 160,
				"h": 4
			}
		}
	},
	"meta": {
		"app": "Adobe Animate",
		"version": "18.0.2.126",
		"image": "userprofile",
		"format": "RGBA8888",
		"size": {
			"w": 1024,
			"h": 1024
		},
		"scale": "1"
	}
}